{
  "timestamp": "2026-03-09T14:43:36.664967",
  "status": "connected",
  "account": {
    "buying_power": 91783.11,
    "cash": -8401.0,
    "day_trade_count": 3,
    "equity": 100184.11,
    "pattern_day_trader": false,
    "portfolio_value": 100184.11,
    "timestamp": "2026-03-09T14:43:36.979686",
    "trading_blocked": false
  },
  "positions": [
    {
      "current_price": 305.45,
      "entry_price": 302.56,
      "market_value": 11912.55,
      "qty": 39,
      "side": "LONG",
      "symbol": "GOOGL",
      "timestamp": "2026-03-09T14:43:37.338222",
      "unrealized_pnl": 112.71,
      "unrealized_pnl_pct": 0.95
    },
    {
      "current_price": 606.83,
      "entry_price": 602.96,
      "market_value": 16991.24,
      "qty": 28,
      "side": "LONG",
      "symbol": "QQQ",
      "timestamp": "2026-03-09T14:43:37.338237",
      "unrealized_pnl": 108.28,
      "unrealized_pnl_pct": 0.64
    },
    {
      "current_price": 677.0,
      "entry_price": 680.14,
      "market_value": 19633.0,
      "qty": 29,
      "side": "LONG",
      "symbol": "SPY",
      "timestamp": "2026-03-09T14:43:37.338244",
      "unrealized_pnl": -91.18,
      "unrealized_pnl_pct": -0.46
    },
    {
      "current_price": 50.27,
      "entry_price": 50.32,
      "market_value": 20056.85,
      "qty": 399,
      "side": "LONG",
      "symbol": "XLF",
      "timestamp": "2026-03-09T14:43:37.338250",
      "unrealized_pnl": -20.83,
      "unrealized_pnl_pct": -0.1
    },
    {
      "current_price": 139.59,
      "entry_price": 137.65,
      "market_value": 20100.96,
      "qty": 144,
      "side": "LONG",
      "symbol": "XLK",
      "timestamp": "2026-03-09T14:43:37.338255",
      "unrealized_pnl": 279.36,
      "unrealized_pnl_pct": 1.41
    },
    {
      "current_price": 154.19,
      "entry_price": 152.8,
      "market_value": 19890.51,
      "qty": 129,
      "side": "LONG",
      "symbol": "XLV",
      "timestamp": "2026-03-09T14:43:37.338261",
      "unrealized_pnl": 179.32,
      "unrealized_pnl_pct": 0.91
    }
  ],
  "orders": [],
  "signals": {
    "confidence": 70,
    "price": 670.61,
    "reasons": [
      "MACD bullish",
      "Price > SMA20"
    ],
    "score": 2,
    "signal": "LONG",
    "timestamp": "2026-03-09T14:43:37.690879"
  },
  "system_status": {
    "last_update": "2026-03-09T12:25:48.787868",
    "mode": "paper",
    "status": "running",
    "uptime_hours": 24
  }
}