{
  "timestamp": "2026-03-12T04:46:46.163143",
  "status": "connected",
  "account": {
    "buying_power": 136898.64,
    "cash": 191137.14,
    "day_trade_count": 26,
    "equity": 102779.71,
    "pattern_day_trader": true,
    "portfolio_value": 102779.71,
    "timestamp": "2026-03-12T04:46:46.489915",
    "trading_blocked": false
  },
  "positions": [
    {
      "current_price": 211.9,
      "entry_price": 212.46,
      "market_value": -26275.6,
      "qty": 124,
      "side": "SHORT",
      "symbol": "AMZN",
      "timestamp": "2026-03-12T04:46:47.155014",
      "unrealized_pnl": 68.98,
      "unrealized_pnl_pct": 0.26
    },
    {
      "current_price": 28.45,
      "entry_price": 27.8,
      "market_value": 15533.7,
      "qty": 546,
      "side": "LONG",
      "symbol": "DBC",
      "timestamp": "2026-03-12T04:46:47.155023",
      "unrealized_pnl": 354.9,
      "unrealized_pnl_pct": 2.34
    },
    {
      "current_price": 403.59,
      "entry_price": 403.11,
      "market_value": -19372.32,
      "qty": 48,
      "side": "SHORT",
      "symbol": "MSFT",
      "timestamp": "2026-03-12T04:46:47.155026",
      "unrealized_pnl": -22.86,
      "unrealized_pnl_pct": -0.12
    },
    {
      "current_price": 605.73,
      "entry_price": 608.25,
      "market_value": -19989.09,
      "qty": 33,
      "side": "SHORT",
      "symbol": "QQQ",
      "timestamp": "2026-03-12T04:46:47.155028",
      "unrealized_pnl": 83.19,
      "unrealized_pnl_pct": 0.41
    },
    {
      "current_price": 78.8,
      "entry_price": 77.34,
      "market_value": 10244.0,
      "qty": 130,
      "side": "LONG",
      "symbol": "SLV",
      "timestamp": "2026-03-12T04:46:47.155031",
      "unrealized_pnl": 189.8,
      "unrealized_pnl_pct": 1.89
    },
    {
      "current_price": 408.62,
      "entry_price": 405.29,
      "market_value": 19613.76,
      "qty": 48,
      "side": "LONG",
      "symbol": "TSLA",
      "timestamp": "2026-03-12T04:46:47.155033",
      "unrealized_pnl": 159.84,
      "unrealized_pnl_pct": 0.82
    },
    {
      "current_price": 112.75,
      "entry_price": 104.12,
      "market_value": 16123.25,
      "qty": 143,
      "side": "LONG",
      "symbol": "USO",
      "timestamp": "2026-03-12T04:46:47.155036",
      "unrealized_pnl": 1233.58,
      "unrealized_pnl_pct": 8.29
    },
    {
      "current_price": 57.4,
      "entry_price": 56.62,
      "market_value": -15383.2,
      "qty": 268,
      "side": "SHORT",
      "symbol": "XLE",
      "timestamp": "2026-03-12T04:46:47.155039",
      "unrealized_pnl": -208.98,
      "unrealized_pnl_pct": -1.38
    },
    {
      "current_price": 49.28,
      "entry_price": 49.82,
      "market_value": -15030.4,
      "qty": 305,
      "side": "SHORT",
      "symbol": "XLF",
      "timestamp": "2026-03-12T04:46:47.155041",
      "unrealized_pnl": 165.22,
      "unrealized_pnl_pct": 1.09
    },
    {
      "current_price": 168.4,
      "entry_price": 169.32,
      "market_value": -14987.6,
      "qty": 89,
      "side": "SHORT",
      "symbol": "XLI",
      "timestamp": "2026-03-12T04:46:47.155043",
      "unrealized_pnl": 82.21,
      "unrealized_pnl_pct": 0.55
    },
    {
      "current_price": 140.1,
      "entry_price": 140.07,
      "market_value": -23676.9,
      "qty": 169,
      "side": "SHORT",
      "symbol": "XLK",
      "timestamp": "2026-03-12T04:46:47.155046",
      "unrealized_pnl": -5.47,
      "unrealized_pnl_pct": -0.02
    },
    {
      "current_price": 46.07,
      "entry_price": 46.06,
      "market_value": -15157.03,
      "qty": 329,
      "side": "SHORT",
      "symbol": "XLU",
      "timestamp": "2026-03-12T04:46:47.155048",
      "unrealized_pnl": -3.29,
      "unrealized_pnl_pct": -0.02
    }
  ],
  "orders": [],
  "signals": {
    "confidence": 50,
    "price": 671.25,
    "reasons": [
      "MACD bearish",
      "Price < SMA20"
    ],
    "score": -1,
    "signal": "NEUTRAL",
    "timestamp": "2026-03-12T04:46:47.500139"
  },
  "system_status": {
    "last_update": "2026-03-11T12:16:39.315549",
    "mode": "paper",
    "status": "running",
    "uptime_hours": 24
  }
}