{
  "timestamp": "2026-03-12T00:49:30.747063",
  "status": "connected",
  "account": {
    "buying_power": 12364.58,
    "cash": 191137.68,
    "day_trade_count": 26,
    "equity": 102699.01,
    "pattern_day_trader": true,
    "portfolio_value": 102699.01,
    "timestamp": "2026-03-12T00:49:31.159601",
    "trading_blocked": false
  },
  "positions": [
    {
      "current_price": 211.39,
      "entry_price": 212.58,
      "market_value": -26212.36,
      "qty": 124,
      "side": "SHORT",
      "symbol": "AMZN",
      "timestamp": "2026-03-12T00:49:31.575110",
      "unrealized_pnl": 147.5,
      "unrealized_pnl_pct": 0.56
    },
    {
      "current_price": 28.57,
      "entry_price": 27.8,
      "market_value": 15599.22,
      "qty": 546,
      "side": "LONG",
      "symbol": "DBC",
      "timestamp": "2026-03-12T00:49:31.575118",
      "unrealized_pnl": 420.42,
      "unrealized_pnl_pct": 2.77
    },
    {
      "current_price": 402.64,
      "entry_price": 403.11,
      "market_value": -19326.72,
      "qty": 48,
      "side": "SHORT",
      "symbol": "MSFT",
      "timestamp": "2026-03-12T00:49:31.575121",
      "unrealized_pnl": 22.74,
      "unrealized_pnl_pct": 0.12
    },
    {
      "current_price": 604.09,
      "entry_price": 607.49,
      "market_value": -19934.97,
      "qty": 33,
      "side": "SHORT",
      "symbol": "QQQ",
      "timestamp": "2026-03-12T00:49:31.575123",
      "unrealized_pnl": 112.28,
      "unrealized_pnl_pct": 0.56
    },
    {
      "current_price": 78.7,
      "entry_price": 77.34,
      "market_value": 10231.0,
      "qty": 130,
      "side": "LONG",
      "symbol": "SLV",
      "timestamp": "2026-03-12T00:49:31.575126",
      "unrealized_pnl": 176.8,
      "unrealized_pnl_pct": 1.76
    },
    {
      "current_price": 406.11,
      "entry_price": 405.29,
      "market_value": 19493.28,
      "qty": 48,
      "side": "LONG",
      "symbol": "TSLA",
      "timestamp": "2026-03-12T00:49:31.575128",
      "unrealized_pnl": 39.36,
      "unrealized_pnl_pct": 0.2
    },
    {
      "current_price": 111.15,
      "entry_price": 104.12,
      "market_value": 15894.45,
      "qty": 143,
      "side": "LONG",
      "symbol": "USO",
      "timestamp": "2026-03-12T00:49:31.575131",
      "unrealized_pnl": 1004.78,
      "unrealized_pnl_pct": 6.75
    },
    {
      "current_price": 56.97,
      "entry_price": 56.86,
      "market_value": -15267.96,
      "qty": 268,
      "side": "SHORT",
      "symbol": "XLE",
      "timestamp": "2026-03-12T00:49:31.575133",
      "unrealized_pnl": -28.92,
      "unrealized_pnl_pct": -0.19
    },
    {
      "current_price": 49.15,
      "entry_price": 49.51,
      "market_value": -14990.75,
      "qty": 305,
      "side": "SHORT",
      "symbol": "XLF",
      "timestamp": "2026-03-12T00:49:31.575135",
      "unrealized_pnl": 109.8,
      "unrealized_pnl_pct": 0.73
    },
    {
      "current_price": 170.8,
      "entry_price": 169.32,
      "market_value": -15201.2,
      "qty": 89,
      "side": "SHORT",
      "symbol": "XLI",
      "timestamp": "2026-03-12T00:49:31.575138",
      "unrealized_pnl": -131.39,
      "unrealized_pnl_pct": -0.87
    },
    {
      "current_price": 139.5,
      "entry_price": 140.06,
      "market_value": -23575.5,
      "qty": 169,
      "side": "SHORT",
      "symbol": "XLK",
      "timestamp": "2026-03-12T00:49:31.575140",
      "unrealized_pnl": 94.15,
      "unrealized_pnl_pct": 0.4
    },
    {
      "current_price": 46.04,
      "entry_price": 46.06,
      "market_value": -15147.16,
      "qty": 329,
      "side": "SHORT",
      "symbol": "XLU",
      "timestamp": "2026-03-12T00:49:31.575143",
      "unrealized_pnl": 6.58,
      "unrealized_pnl_pct": 0.04
    }
  ],
  "orders": [],
  "signals": {
    "confidence": 50,
    "price": 671.25,
    "reasons": [
      "MACD bearish",
      "Price < SMA20"
    ],
    "score": -1,
    "signal": "NEUTRAL",
    "timestamp": "2026-03-12T00:49:32.014244"
  },
  "system_status": {
    "last_update": "2026-03-11T12:16:39.315549",
    "mode": "paper",
    "status": "running",
    "uptime_hours": 24
  }
}