{
  "timestamp": "2026-04-03T09:16:52.285253",
  "status": "connected",
  "account": {
    "equity": 88318.38,
    "buying_power": 193152.64,
    "cash": 48288.16,
    "portfolio_value": 88318.38,
    "pattern_day_trader": true,
    "trading_blocked": false,
    "day_trade_count": 61,
    "timestamp": "2026-04-03T09:16:52.688563"
  },
  "positions": [
    {
      "symbol": "BTCUSD",
      "qty": 0,
      "side": "LONG",
      "entry_price": 67099.646882269,
      "current_price": 66935.647,
      "market_value": 22080.240862,
      "unrealized_pnl": -54.09908,
      "unrealized_pnl_pct": -0.244,
      "timestamp": "2026-04-03T09:16:53.054721"
    },
    {
      "symbol": "SOLUSD",
      "qty": 223,
      "side": "LONG",
      "entry_price": 80.696965067,
      "current_price": 80.18,
      "market_value": 17949.979345,
      "unrealized_pnl": -115.733503,
      "unrealized_pnl_pct": -0.641,
      "timestamp": "2026-04-03T09:16:53.054745"
    }
  ],
  "orders": [],
  "system_status": {
    "status": "running",
    "mode": "paper",
    "last_update": "2026-04-03T09:16:53.415494",
    "uptime_hours": 24
  },
  "signals": {
    "signal": "HOLD",
    "confidence": 0,
    "timestamp": "2026-04-03T09:16:53.415516"
  }
}