{
  "timestamp": "2026-03-28T09:38:48.032287",
  "status": "connected",
  "account": {
    "equity": 93654.48,
    "buying_power": 336746.2,
    "cash": 84186.55,
    "portfolio_value": 93654.48,
    "pattern_day_trader": true,
    "trading_blocked": false,
    "day_trade_count": 36,
    "timestamp": "2026-03-28T09:38:48.384511"
  },
  "positions": [
    {
      "symbol": "BTCUSD",
      "qty": 0,
      "side": "LONG",
      "entry_price": 66024.9,
      "current_price": 66973.5,
      "market_value": 4737.974623,
      "unrealized_pnl": 67.107777,
      "unrealized_pnl_pct": 1.437,
      "timestamp": "2026-03-28T09:38:48.745843"
    },
    {
      "symbol": "SOLUSD",
      "qty": 56,
      "side": "LONG",
      "entry_price": 82.804710484,
      "current_price": 83.856,
      "market_value": 4729.950845,
      "unrealized_pnl": 59.298652,
      "unrealized_pnl_pct": 1.27,
      "timestamp": "2026-03-28T09:38:48.745890"
    }
  ],
  "orders": [],
  "system_status": {
    "status": "running",
    "mode": "paper",
    "last_update": "2026-03-28T09:38:49.103295",
    "uptime_hours": 24
  },
  "signals": {
    "signal": "HOLD",
    "confidence": 0,
    "timestamp": "2026-03-28T09:38:49.103322"
  }
}