{
  "timestamp": "2026-04-07T01:23:51.297303",
  "status": "connected",
  "account": {
    "equity": 88569.07,
    "buying_power": 191557.08,
    "cash": 47889.27,
    "portfolio_value": 88569.07,
    "pattern_day_trader": true,
    "trading_blocked": false,
    "day_trade_count": 65,
    "timestamp": "2026-04-07T01:23:51.678286"
  },
  "positions": [
    {
      "symbol": "BTCUSD",
      "qty": 0,
      "side": "LONG",
      "entry_price": 67099.646882269,
      "current_price": 68849.87,
      "market_value": 22711.690721,
      "unrealized_pnl": 577.350779,
      "unrealized_pnl_pct": 2.608,
      "timestamp": "2026-04-07T01:23:52.038518"
    },
    {
      "symbol": "SOLUSD",
      "qty": 223,
      "side": "LONG",
      "entry_price": 80.696965067,
      "current_price": 80.261,
      "market_value": 17968.112899,
      "unrealized_pnl": -97.599949,
      "unrealized_pnl_pct": -0.54,
      "timestamp": "2026-04-07T01:23:52.038548"
    }
  ],
  "orders": [],
  "system_status": {
    "status": "running",
    "mode": "paper",
    "last_update": "2026-04-07T01:23:52.381951",
    "uptime_hours": 24
  },
  "signals": {
    "signal": "HOLD",
    "confidence": 0,
    "timestamp": "2026-04-07T01:23:52.381971"
  }
}