{
  "timestamp": "2026-03-29T07:00:41.120225",
  "status": "connected",
  "account": {
    "equity": 93496.0,
    "buying_power": 336746.2,
    "cash": 84186.55,
    "portfolio_value": 93496.0,
    "pattern_day_trader": true,
    "trading_blocked": false,
    "day_trade_count": 36,
    "timestamp": "2026-03-29T07:00:41.485185"
  },
  "positions": [
    {
      "symbol": "BTCUSD",
      "qty": 0,
      "side": "LONG",
      "entry_price": 66024.9,
      "current_price": 66404.593,
      "market_value": 4697.727855,
      "unrealized_pnl": 26.861009,
      "unrealized_pnl_pct": 0.575,
      "timestamp": "2026-03-29T07:00:41.845245"
    },
    {
      "symbol": "SOLUSD",
      "qty": 56,
      "side": "LONG",
      "entry_price": 82.804710484,
      "current_price": 81.76,
      "market_value": 4611.724636,
      "unrealized_pnl": -58.927557,
      "unrealized_pnl_pct": -1.262,
      "timestamp": "2026-03-29T07:00:41.845279"
    }
  ],
  "orders": [],
  "system_status": {
    "status": "running",
    "mode": "paper",
    "last_update": "2026-03-29T07:00:42.210403",
    "uptime_hours": 24
  },
  "signals": {
    "signal": "HOLD",
    "confidence": 0,
    "timestamp": "2026-03-29T07:00:42.210432"
  }
}