[{"current_price":241.3,"entry_price":238.78,"market_value":6997.7,"qty":29,"side":"LONG","symbol":"JNJ","timestamp":"2026-04-14T10:21:13.552106","unrealized_pnl":73.08,"unrealized_pnl_pct":1.05},{"current_price":311.24,"entry_price":311.39,"market_value":6847.28,"qty":22,"side":"LONG","symbol":"JPM","timestamp":"2026-04-14T10:21:13.552134","unrealized_pnl":-3.4,"unrealized_pnl_pct":-0.05},{"current_price":937.75,"entry_price":907.15,"market_value":6564.25,"qty":7,"side":"LONG","symbol":"SNDK","timestamp":"2026-04-14T10:21:13.552159","unrealized_pnl":214.23,"unrealized_pnl_pct":3.37},{"current_price":40.64,"entry_price":41.11,"market_value":6746.24,"qty":166,"side":"LONG","symbol":"TVTX","timestamp":"2026-04-14T10:21:13.552174","unrealized_pnl":-78.02,"unrealized_pnl_pct":-1.14},{"current_price":149.08,"entry_price":149.06,"market_value":7006.76,"qty":47,"side":"LONG","symbol":"XLV","timestamp":"2026-04-14T10:21:13.552187","unrealized_pnl":0.94,"unrealized_pnl_pct":0.01}]