[{"current_price":455.82,"entry_price":447.55,"market_value":13218.78,"qty":29,"side":"LONG","symbol":"CRWD","timestamp":"2026-04-27T11:12:01.825951","unrealized_pnl":239.83,"unrealized_pnl_pct":1.85},{"current_price":352.91,"entry_price":343.19,"market_value":13763.49,"qty":39,"side":"LONG","symbol":"GOOGL","timestamp":"2026-04-27T11:12:01.825974","unrealized_pnl":379.08,"unrealized_pnl_pct":2.83},{"current_price":10.73,"entry_price":10.85,"market_value":7149.51,"qty":666,"side":"LONG","symbol":"NOK","timestamp":"2026-04-27T11:12:01.825982","unrealized_pnl":-76.59,"unrealized_pnl_pct":-1.06},{"current_price":49.76,"entry_price":50.15,"market_value":13384.09,"qty":269,"side":"LONG","symbol":"PYPL","timestamp":"2026-04-27T11:12:01.825990","unrealized_pnl":-106.25,"unrealized_pnl_pct":-0.79}]