[{"current_price":67.88,"entry_price":67.26,"market_value":16086.38,"qty":237,"side":"LONG","symbol":"INTC","timestamp":"2026-04-16T11:52:02.994373","unrealized_pnl":146.01,"unrealized_pnl_pct":0.92},{"current_price":56.66,"entry_price":56.52,"market_value":18244.52,"qty":322,"side":"LONG","symbol":"OXY","timestamp":"2026-04-16T11:52:02.994398","unrealized_pnl":45.08,"unrealized_pnl_pct":0.25},{"current_price":86.36,"entry_price":86.91,"market_value":-17703.8,"qty":205,"side":"SHORT","symbol":"TLT","timestamp":"2026-04-16T11:52:02.994406","unrealized_pnl":112.75,"unrealized_pnl_pct":0.63},{"current_price":10.75,"entry_price":10.66,"market_value":14928.28,"qty":1389,"side":"LONG","symbol":"UNG","timestamp":"2026-04-16T11:52:02.994413","unrealized_pnl":121.54,"unrealized_pnl_pct":0.82},{"current_price":126.5,"entry_price":127.16,"market_value":16698.0,"qty":132,"side":"LONG","symbol":"USO","timestamp":"2026-04-16T11:52:02.994421","unrealized_pnl":-87.18,"unrealized_pnl_pct":-0.52},{"current_price":124.48,"entry_price":125.35,"market_value":17801.35,"qty":143,"side":"LONG","symbol":"WMT","timestamp":"2026-04-16T11:52:02.994429","unrealized_pnl":-123.69,"unrealized_pnl_pct":-0.69}]