[{"current_price":112.14,"entry_price":105.88,"market_value":7401.24,"qty":66,"side":"LONG","symbol":"CRWV","timestamp":"2026-04-13T12:31:44.235369","unrealized_pnl":413.16,"unrealized_pnl_pct":5.91},{"current_price":6.24,"entry_price":6.22,"market_value":-7151.55,"qty":1147,"side":"SHORT","symbol":"EOSE","timestamp":"2026-04-13T12:31:44.235401","unrealized_pnl":-17.2,"unrealized_pnl_pct":-0.24},{"current_price":181.95,"entry_price":179.89,"market_value":5822.4,"qty":32,"side":"LONG","symbol":"NET","timestamp":"2026-04-13T12:31:44.235410","unrealized_pnl":65.92,"unrealized_pnl_pct":1.15},{"current_price":10.29,"entry_price":10.22,"market_value":-7175.61,"qty":697,"side":"SHORT","symbol":"NOK","timestamp":"2026-04-13T12:31:44.235416","unrealized_pnl":-52.27,"unrealized_pnl_pct":-0.73},{"current_price":25.88,"entry_price":24.69,"market_value":7348.5,"qty":284,"side":"LONG","symbol":"SMCI","timestamp":"2026-04-13T12:31:44.235423","unrealized_pnl":336.56,"unrealized_pnl_pct":4.8},{"current_price":127.99,"entry_price":133.45,"market_value":9599.25,"qty":75,"side":"LONG","symbol":"USO","timestamp":"2026-04-13T12:31:44.235429","unrealized_pnl":-409.63,"unrealized_pnl_pct":-4.09},{"current_price":17.41,"entry_price":17.14,"market_value":6250.19,"qty":359,"side":"LONG","symbol":"VALE","timestamp":"2026-04-13T12:31:44.235435","unrealized_pnl":96.93,"unrealized_pnl_pct":1.57}]