[{"current_price":111.66,"entry_price":105.88,"market_value":7369.56,"qty":66,"side":"LONG","symbol":"CRWV","timestamp":"2026-04-13T10:04:06.803338","unrealized_pnl":381.48,"unrealized_pnl_pct":5.46},{"current_price":6.17,"entry_price":6.22,"market_value":-7076.99,"qty":1147,"side":"SHORT","symbol":"EOSE","timestamp":"2026-04-13T10:04:06.803349","unrealized_pnl":57.35,"unrealized_pnl_pct":0.8},{"current_price":182.03,"entry_price":179.89,"market_value":5824.96,"qty":32,"side":"LONG","symbol":"NET","timestamp":"2026-04-13T10:04:06.803354","unrealized_pnl":68.48,"unrealized_pnl_pct":1.19},{"current_price":10.36,"entry_price":10.22,"market_value":-7220.92,"qty":697,"side":"SHORT","symbol":"NOK","timestamp":"2026-04-13T10:04:06.803357","unrealized_pnl":-97.58,"unrealized_pnl_pct":-1.37},{"current_price":25.86,"entry_price":24.69,"market_value":7345.66,"qty":284,"side":"LONG","symbol":"SMCI","timestamp":"2026-04-13T10:04:06.803362","unrealized_pnl":333.72,"unrealized_pnl_pct":4.76},{"current_price":129.92,"entry_price":133.45,"market_value":9743.88,"qty":75,"side":"LONG","symbol":"USO","timestamp":"2026-04-13T10:04:06.803365","unrealized_pnl":-265.0,"unrealized_pnl_pct":-2.65},{"current_price":17.34,"entry_price":17.14,"market_value":6225.06,"qty":359,"side":"LONG","symbol":"VALE","timestamp":"2026-04-13T10:04:06.803369","unrealized_pnl":71.8,"unrealized_pnl_pct":1.17}]