[{"current_price":111.07,"entry_price":105.88,"market_value":7330.62,"qty":66,"side":"LONG","symbol":"CRWV","timestamp":"2026-04-13T08:35:21.654827","unrealized_pnl":342.54,"unrealized_pnl_pct":4.9},{"current_price":6.24,"entry_price":6.22,"market_value":-7151.55,"qty":1147,"side":"SHORT","symbol":"EOSE","timestamp":"2026-04-13T08:35:21.654867","unrealized_pnl":-17.2,"unrealized_pnl_pct":-0.24},{"current_price":180.98,"entry_price":179.89,"market_value":5791.28,"qty":32,"side":"LONG","symbol":"NET","timestamp":"2026-04-13T08:35:21.654883","unrealized_pnl":34.8,"unrealized_pnl_pct":0.6},{"current_price":10.15,"entry_price":10.22,"market_value":-7078.03,"qty":697,"side":"SHORT","symbol":"NOK","timestamp":"2026-04-13T08:35:21.654898","unrealized_pnl":45.3,"unrealized_pnl_pct":0.64},{"current_price":25.5,"entry_price":24.69,"market_value":7240.58,"qty":284,"side":"LONG","symbol":"SMCI","timestamp":"2026-04-13T08:35:21.654911","unrealized_pnl":228.64,"unrealized_pnl_pct":3.26},{"current_price":133.08,"entry_price":133.45,"market_value":9981.0,"qty":75,"side":"LONG","symbol":"USO","timestamp":"2026-04-13T08:35:21.654925","unrealized_pnl":-27.88,"unrealized_pnl_pct":-0.28},{"current_price":17.15,"entry_price":17.14,"market_value":6156.85,"qty":359,"side":"LONG","symbol":"VALE","timestamp":"2026-04-13T08:35:21.654938","unrealized_pnl":3.59,"unrealized_pnl_pct":0.06}]