[{"current_price":455.5,"entry_price":447.55,"market_value":13209.5,"qty":29,"side":"LONG","symbol":"CRWD","timestamp":"2026-04-27T08:19:24.919277","unrealized_pnl":230.55,"unrealized_pnl_pct":1.78},{"current_price":351.17,"entry_price":343.19,"market_value":13695.63,"qty":39,"side":"LONG","symbol":"GOOGL","timestamp":"2026-04-27T08:19:24.919286","unrealized_pnl":311.22,"unrealized_pnl_pct":2.33},{"current_price":209.71,"entry_price":209.84,"market_value":1258.27,"qty":6,"side":"LONG","symbol":"NVDA","timestamp":"2026-04-27T08:19:24.919289","unrealized_pnl":-0.77,"unrealized_pnl_pct":-0.06},{"current_price":50.02,"entry_price":50.15,"market_value":13456.73,"qty":269,"side":"LONG","symbol":"PYPL","timestamp":"2026-04-27T08:19:24.919292","unrealized_pnl":-33.62,"unrealized_pnl_pct":-0.25},{"current_price":712.84,"entry_price":713.86,"market_value":17108.16,"qty":24,"side":"LONG","symbol":"SPY","timestamp":"2026-04-27T08:19:24.919295","unrealized_pnl":-24.48,"unrealized_pnl_pct":-0.14}]