[{"current_price":112.3,"entry_price":105.88,"market_value":7411.8,"qty":66,"side":"LONG","symbol":"CRWV","timestamp":"2026-04-13T08:05:26.051461","unrealized_pnl":423.72,"unrealized_pnl_pct":6.06},{"current_price":6.26,"entry_price":6.22,"market_value":-7185.95,"qty":1147,"side":"SHORT","symbol":"EOSE","timestamp":"2026-04-13T08:05:26.051501","unrealized_pnl":-51.62,"unrealized_pnl_pct":-0.72},{"current_price":180.04,"entry_price":179.89,"market_value":5761.44,"qty":32,"side":"LONG","symbol":"NET","timestamp":"2026-04-13T08:05:26.051517","unrealized_pnl":4.96,"unrealized_pnl_pct":0.09},{"current_price":10.23,"entry_price":10.22,"market_value":-7130.31,"qty":697,"side":"SHORT","symbol":"NOK","timestamp":"2026-04-13T08:05:26.051531","unrealized_pnl":-6.97,"unrealized_pnl_pct":-0.1},{"current_price":25.3,"entry_price":24.69,"market_value":7183.78,"qty":284,"side":"LONG","symbol":"SMCI","timestamp":"2026-04-13T08:05:26.051544","unrealized_pnl":171.84,"unrealized_pnl_pct":2.45},{"current_price":132.34,"entry_price":133.45,"market_value":9925.5,"qty":75,"side":"LONG","symbol":"USO","timestamp":"2026-04-13T08:05:26.051558","unrealized_pnl":-83.38,"unrealized_pnl_pct":-0.83},{"current_price":17.16,"entry_price":17.14,"market_value":6158.65,"qty":359,"side":"LONG","symbol":"VALE","timestamp":"2026-04-13T08:05:26.051571","unrealized_pnl":5.38,"unrealized_pnl_pct":0.09}]