[{"current_price":68.2,"entry_price":67.26,"market_value":16164.58,"qty":237,"side":"LONG","symbol":"INTC","timestamp":"2026-04-16T12:08:26.020887","unrealized_pnl":224.22,"unrealized_pnl_pct":1.41},{"current_price":56.69,"entry_price":56.52,"market_value":18254.18,"qty":322,"side":"LONG","symbol":"OXY","timestamp":"2026-04-16T12:08:26.020894","unrealized_pnl":54.74,"unrealized_pnl_pct":0.3},{"current_price":86.35,"entry_price":86.91,"market_value":-17701.75,"qty":205,"side":"SHORT","symbol":"TLT","timestamp":"2026-04-16T12:08:26.020897","unrealized_pnl":114.8,"unrealized_pnl_pct":0.64},{"current_price":10.78,"entry_price":10.66,"market_value":14973.42,"qty":1389,"side":"LONG","symbol":"UNG","timestamp":"2026-04-16T12:08:26.020899","unrealized_pnl":166.68,"unrealized_pnl_pct":1.13},{"current_price":126.47,"entry_price":127.16,"market_value":16694.04,"qty":132,"side":"LONG","symbol":"USO","timestamp":"2026-04-16T12:08:26.020901","unrealized_pnl":-91.14,"unrealized_pnl_pct":-0.54},{"current_price":124.64,"entry_price":125.35,"market_value":17823.52,"qty":143,"side":"LONG","symbol":"WMT","timestamp":"2026-04-16T12:08:26.020903","unrealized_pnl":-101.53,"unrealized_pnl_pct":-0.57}]