[{"current_price":455.74,"entry_price":447.55,"market_value":13216.46,"qty":29,"side":"LONG","symbol":"CRWD","timestamp":"2026-04-27T10:11:52.404190","unrealized_pnl":237.51,"unrealized_pnl_pct":1.83},{"current_price":351.95,"entry_price":343.19,"market_value":13726.05,"qty":39,"side":"LONG","symbol":"GOOGL","timestamp":"2026-04-27T10:11:52.404223","unrealized_pnl":341.64,"unrealized_pnl_pct":2.55},{"current_price":10.76,"entry_price":10.85,"market_value":7162.83,"qty":666,"side":"LONG","symbol":"NOK","timestamp":"2026-04-27T10:11:52.404242","unrealized_pnl":-63.27,"unrealized_pnl_pct":-0.88},{"current_price":49.85,"entry_price":50.15,"market_value":13411.0,"qty":269,"side":"LONG","symbol":"PYPL","timestamp":"2026-04-27T10:11:52.404260","unrealized_pnl":-79.36,"unrealized_pnl_pct":-0.59}]