[{"current_price":59.59,"entry_price":59.31,"market_value":-9713.17,"qty":163,"side":"SHORT","symbol":"AFRM","timestamp":"2026-04-15T12:11:22.125760","unrealized_pnl":-45.64,"unrealized_pnl_pct":-0.47},{"current_price":394.57,"entry_price":388.0,"market_value":10258.82,"qty":26,"side":"LONG","symbol":"AVGO","timestamp":"2026-04-15T12:11:22.125768","unrealized_pnl":170.95,"unrealized_pnl_pct":1.7},{"current_price":64.67,"entry_price":64.29,"market_value":17914.97,"qty":277,"side":"LONG","symbol":"INTC","timestamp":"2026-04-15T12:11:22.125772","unrealized_pnl":106.64,"unrealized_pnl_pct":0.6},{"current_price":413.48,"entry_price":406.91,"market_value":-10336.88,"qty":25,"side":"SHORT","symbol":"MSFT","timestamp":"2026-04-15T12:11:22.125776","unrealized_pnl":-164.25,"unrealized_pnl_pct":-1.62},{"current_price":124.83,"entry_price":124.81,"market_value":17725.86,"qty":142,"side":"LONG","symbol":"WMT","timestamp":"2026-04-15T12:11:22.125779","unrealized_pnl":2.84,"unrealized_pnl_pct":0.02}]