[{"current_price":454.87,"entry_price":447.55,"market_value":13191.08,"qty":29,"side":"LONG","symbol":"CRWD","timestamp":"2026-04-27T12:51:47.967420","unrealized_pnl":212.13,"unrealized_pnl_pct":1.63},{"current_price":350.97,"entry_price":343.19,"market_value":13687.83,"qty":39,"side":"LONG","symbol":"GOOGL","timestamp":"2026-04-27T12:51:47.967449","unrealized_pnl":303.42,"unrealized_pnl_pct":2.27},{"current_price":10.76,"entry_price":10.85,"market_value":7162.83,"qty":666,"side":"LONG","symbol":"NOK","timestamp":"2026-04-27T12:51:47.967466","unrealized_pnl":-63.27,"unrealized_pnl_pct":-0.88},{"current_price":49.84,"entry_price":50.15,"market_value":13405.61,"qty":269,"side":"LONG","symbol":"PYPL","timestamp":"2026-04-27T12:51:47.967481","unrealized_pnl":-84.73,"unrealized_pnl_pct":-0.63}]