[{"current_price":453.92,"entry_price":447.55,"market_value":13163.68,"qty":29,"side":"LONG","symbol":"CRWD","timestamp":"2026-04-27T12:09:34.660670","unrealized_pnl":184.73,"unrealized_pnl_pct":1.42},{"current_price":352.22,"entry_price":343.19,"market_value":13736.58,"qty":39,"side":"LONG","symbol":"GOOGL","timestamp":"2026-04-27T12:09:34.660706","unrealized_pnl":352.17,"unrealized_pnl_pct":2.63},{"current_price":10.74,"entry_price":10.85,"market_value":7156.17,"qty":666,"side":"LONG","symbol":"NOK","timestamp":"2026-04-27T12:09:34.660723","unrealized_pnl":-69.93,"unrealized_pnl_pct":-0.97},{"current_price":49.84,"entry_price":50.15,"market_value":13405.61,"qty":269,"side":"LONG","symbol":"PYPL","timestamp":"2026-04-27T12:09:34.660738","unrealized_pnl":-84.73,"unrealized_pnl_pct":-0.63}]